rga/__init__.py
rga/base/__init__.py
rga/base/commands.py
rga/base/communications.py
rga/base/component.py
rga/base/exceptions.py
rga/base/indexcommands.py
rga/base/instrument.py
rga/base/serial_ports.py
rga/rga100/__init__.py
rga/rga100/commands.py
rga/rga100/components.py
rga/rga100/errors.py
rga/rga100/rga.py
rga/rga100/scans.py
rga/rga100/sicp.py
rga-0.1.14.dist-info/LICENSE.txt
rga-0.1.14.dist-info/LICENSE.txtold
rga-0.1.14.dist-info/METADATA
rga-0.1.14.dist-info/WHEEL
rga-0.1.14.dist-info/top_level.txt
rga-0.1.14.dist-info/RECORD
