Metadata-Version: 2.1
Name: rga
Version: 0.1.14
Summary: Communication package for SRS RGA
Author: Chulhoon Kim
Author-email: chulhoonk@yahoo.com
License: MIT license
Keywords: RGA,residual gas analyzer,SRS,Stanford Research Systems
Classifier: Development Status :: 3 - Alpha
Classifier: Intended Audience :: Science/Research
Classifier: License :: OSI Approved :: MIT License
Classifier: Operating System :: OS Independent
Classifier: Programming Language :: Python :: 3.7
Classifier: Topic :: Scientific/Engineering
License-File: LICENSE.txt
License-File: LICENSE.txtold
Requires-Dist: pyserial (>=3)
Requires-Dist: numpy
